Metadata-Version: 2.1
Name: typing-tools
Version: 0.1.4
Summary: Provides tools for typing in Python 3.6.
Home-page: https://gitlab.com/Hares/typing-tools
Author: Peter Zaitcev / USSX Hares
Author-email: ussx-hares@yandex.ru
License: MIT
Platform: UNKNOWN
Classifier: License :: OSI Approved :: MIT License
Classifier: Programming Language :: Python
Classifier: Programming Language :: Python :: 3
Classifier: Programming Language :: Python :: 3.6
Classifier: Programming Language :: Python :: Implementation :: CPython
Classifier: Programming Language :: Python :: Implementation :: PyPy
Requires-Python: >=3.6.0
